{"sheet_uid":"Efo4QYmiuB","title":"Hey Soul Sister","artist_uid":"ms4xcTG0sD","bpm":97,"capo":4,"origin":0,"video_id":"-lEPX2fF4Ls","lyrics_chord":"E   B   B           C#m   C#m           A \nHey-ay, Hey-ay-AY-ay-ay, Hey-ay-AY-ay-ay \n \n     E               B \nYour lipstick stains \n                        C#m              A \nOn the front lobe of my left side brains \n                     E \nI knew I wouldn't forget you \n                  B               C#m  A B \nAnd so I went and let you blow my mind \n     E             B \nYour sweet moonbeam \n                          C#m              A \nThe smell of you in every single dream I dream \n                   E \nI knew when we collided \n                       B                     C#m   A  B \nYou're the one I had decided who's one of my kind \n \nA \nHey, soul sister \nB              E             A \nAin't that Mr. Mister on the radio, stereo \n    B \nThe way you move ain't fair you know \nA \nHey, soul sister \n B                          A           B \nI don't wanna miss a single thing you do \n   E \ntonight \n \n    B   B            C#m  C#m           A \nHey-ay, Hey-ay-AY-ay-ay, Hey-ay-AY-ay-ay \n \nE           B \nJust in time \n                       C#m                  A \nI'm so glad you have a one track mind like me \n                   E \nYou gave my life direction \n                    B                 C#m  A  B \na game show love connection we can't deny \n    E           B \nI'm so obsessed \n                                C#m                  A \nMy heart is bound to beat right out of my untrimmed chest \n             E                            B \nI believe in you, like a virgin you're madonna \n                     C#m              A   B \nAnd I'm always gonna wanna blow your mind \n \nA \nHey, soul sister \n     B                       A \nAin't that Mr. Mister on the radio, stereo \n    B \nThe way you move ain't fair you know \nA \nHey, soul sister \n B                          A           B \nI don't wanna miss a single thing you do \n  E \ntonight \n                E \nThe way you can cut a rug \nB                               C#m \nWatching you is the only drug I need \n \nSo gangsta, I'm so thug \n           A \nYou're the only one I'm dreaming of \n    E                              B \nYou see, I can be myself now finally \n                                 C#m \nIn fact, there's nothing I can't be \n           B \nI want the world to see \n       A       B \nYou'll be with me \n \nA \nHey, soul sister \nB                            A \nAin't that Mr. Mister on the radio, stereo \n    B \nThe way you move ain't fair you know \nA \nHey, soul sister \nB                           A \nI don't wanna miss a single thing you do \n   B \ntonight \n \nA \nHey, soul sister \n B                          A           B \nI don't wanna miss a single thing you do \n   E \ntonight \n \n    B                C#m               A  B \nHey-ay, Hey-ay-AY-ay-ay, Hey-ay-AY-ay-ay \n   E \nTonight \n    B                C#m               A  B \nHey-ay, Hey-ay-AY-ay-ay, Hey-ay-AY-ay-ay \n   E \nTonight \n \n \n \n \n \n","chord_list":"[{\"beat_count\":3,\"chord\":\"E\",\"time_ms\":2960,\"time_ms_arr\":[2960,3580,4200]},{\"beat_count\":2,\"chord\":\"B\",\"time_ms\":4780,\"time_ms_arr\":[4780,5420]},{\"beat_count\":2,\"chord\":\"B\",\"time_ms\":6040,\"time_ms_arr\":[6040,6680]},{\"beat_count\":2,\"chord\":\"C#m\",\"time_ms\":7260,\"time_ms_arr\":[7260,7900]},{\"beat_count\":2,\"chord\":\"C#m\",\"time_ms\":8520,\"time_ms_arr\":[8520,9140]},{\"beat_count\":4,\"chord\":\"A\",\"time_ms\":9740,\"time_ms_arr\":[9740,10380,11000,11620]},{\"beat_count\":4,\"chord\":\"E\",\"time_ms\":12260,\"time_ms_arr\":[12260,12860,13460,14080]},{\"beat_count\":4,\"chord\":\"B\",\"time_ms\":14720,\"time_ms_arr\":[14720,15320,15940,16560]},{\"beat_count\":4,\"chord\":\"C#m\",\"time_ms\":17140,\"time_ms_arr\":[17140,17780,18400,19020]},{\"beat_count\":4,\"chord\":\"A\",\"time_ms\":19620,\"time_ms_arr\":[19620,20260,20860,21500]},{\"beat_count\":4,\"chord\":\"E\",\"time_ms\":22100,\"time_ms_arr\":[22100,22740,23340,23980]},{\"beat_count\":4,\"chord\":\"B\",\"time_ms\":24620,\"time_ms_arr\":[24620,25220,25820,26460]},{\"beat_count\":4,\"chord\":\"C#m\",\"time_ms\":27060,\"time_ms_arr\":[27060,27700,28300,28920]},{\"beat_count\":2,\"chord\":\"A\",\"time_ms\":29560,\"time_ms_arr\":[29560,30160]},{\"beat_count\":2,\"chord\":\"B\",\"time_ms\":30780,\"time_ms_arr\":[30780,31400]},{\"beat_count\":4,\"chord\":\"E\",\"time_ms\":32020.000000000004,\"time_ms_arr\":[32020.000000000004,32640,33260,33900]},{\"beat_count\":4,\"chord\":\"B\",\"time_ms\":34500,\"time_ms_arr\":[34500,35120,35740,36340]},{\"beat_count\":4,\"chord\":\"C#m\",\"time_ms\":37000,\"time_ms_arr\":[37000,37600,38200,38820]},{\"beat_count\":4,\"chord\":\"A\",\"time_ms\":39460,\"time_ms_arr\":[39460,40080,40680,41300]},{\"beat_count\":4,\"chord\":\"E\",\"time_ms\":41900,\"time_ms_arr\":[41900,42540,43160,43780]},{\"beat_count\":4,\"chord\":\"B\",\"time_ms\":44360,\"time_ms_arr\":[44360,45020,45620,46240]},{\"beat_count\":4,\"chord\":\"C#m\",\"time_ms\":46880,\"time_ms_arr\":[46880,47480,48100,48720]},{\"beat_count\":2,\"chord\":\"A\",\"time_ms\":49360,\"time_ms_arr\":[49360,49960]},{\"beat_count\":2,\"chord\":\"B\",\"time_ms\":50580,\"time_ms_arr\":[50580,51200]},{\"beat_count\":4,\"chord\":\"A\",\"time_ms\":51780,\"time_ms_arr\":[51780,52440,53060,53680]},{\"beat_count\":2,\"chord\":\"B\",\"time_ms\":54300,\"time_ms_arr\":[54300,54900]},{\"bar_index\":0,\"beat_index\":0,\"beat_count\":2,\"chord\":\"E\",\"time_ms\":55540,\"time_ms_arr\":[55540,56140],\"passed\":false},{\"beat_count\":4,\"chord\":\"A\",\"time_ms\":56780,\"time_ms_arr\":[56780,57380,57980,58620]},{\"beat_count\":4,\"chord\":\"B\",\"time_ms\":59260,\"time_ms_arr\":[59260,59860,60480,61100]},{\"beat_count\":4,\"chord\":\"A\",\"time_ms\":61740,\"time_ms_arr\":[61740,62320,62940,63580]},{\"beat_count\":4,\"chord\":\"B\",\"time_ms\":64220,\"time_ms_arr\":[64220,64819.99999999999,65420,66040]},{\"beat_count\":4,\"chord\":\"A\",\"time_ms\":66700,\"time_ms_arr\":[66700,67280,67900,68520]},{\"beat_count\":4,\"chord\":\"B\",\"time_ms\":69140,\"time_ms_arr\":[69140,69740,70360,70980]},{\"beat_count\":4,\"chord\":\"E\",\"time_ms\":71620,\"time_ms_arr\":[71620,72220,72840,73460]},{\"beat_count\":2,\"chord\":\"B\",\"time_ms\":74100,\"time_ms_arr\":[74100,74700]},{\"bar_index\":0,\"beat_index\":0,\"beat_count\":2,\"chord\":\"B\",\"time_ms\":75300,\"time_ms_arr\":[75300,75940],\"passed\":false},{\"beat_count\":2,\"chord\":\"C#m\",\"time_ms\":76580,\"time_ms_arr\":[76580,77180]},{\"beat_count\":2,\"chord\":\"C#m\",\"time_ms\":77800,\"time_ms_arr\":[77800,78420]},{\"beat_count\":4,\"chord\":\"A\",\"time_ms\":79060,\"time_ms_arr\":[79060,79660,80260,80900]},{\"beat_count\":4,\"chord\":\"E\",\"time_ms\":81540,\"time_ms_arr\":[81540,82140,82740,83360]},{\"beat_count\":4,\"chord\":\"B\",\"time_ms\":84020,\"time_ms_arr\":[84020,84600,85220,85840]},{\"beat_count\":4,\"chord\":\"C#m\",\"time_ms\":86460,\"time_ms_arr\":[86460,87060,87700,88300]},{\"beat_count\":4,\"chord\":\"A\",\"time_ms\":88900,\"time_ms_arr\":[88900,89540,90160,90780]},{\"beat_count\":4,\"chord\":\"E\",\"time_ms\":91380,\"time_ms_arr\":[91380,92020,92620,93260]},{\"beat_count\":3,\"chord\":\"B\",\"time_ms\":93840,\"time_ms_arr\":[93840,94500,95160]},{\"beat_count\":3,\"chord\":\"C#m\",\"time_ms\":96040,\"time_ms_arr\":[96040,96980,97900]},{\"beat_count\":2,\"chord\":\"A\",\"time_ms\":98780,\"time_ms_arr\":[98780,99440]},{\"beat_count\":2,\"chord\":\"B\",\"time_ms\":100060,\"time_ms_arr\":[100060,100680]},{\"beat_count\":4,\"chord\":\"E\",\"time_ms\":101300,\"time_ms_arr\":[101300,101920,102520,103160]},{\"beat_count\":4,\"chord\":\"B\",\"time_ms\":103780,\"time_ms_arr\":[103780,104400,105020,105640]},{\"beat_count\":4,\"chord\":\"C#m\",\"time_ms\":106260,\"time_ms_arr\":[106260,106880,107500,108100]},{\"beat_count\":4,\"chord\":\"A\",\"time_ms\":108720,\"time_ms_arr\":[108720,109340,109960,110580]},{\"beat_count\":4,\"chord\":\"E\",\"time_ms\":111200,\"time_ms_arr\":[111200,111820,112420,113060]},{\"beat_count\":4,\"chord\":\"B\",\"time_ms\":113680,\"time_ms_arr\":[113680,114300,114920,115540]},{\"beat_count\":4,\"chord\":\"C#m\",\"time_ms\":116140,\"time_ms_arr\":[116140,116780,117400,118000]},{\"beat_count\":2,\"chord\":\"A\",\"time_ms\":118620,\"time_ms_arr\":[118620,119240]},{\"beat_count\":2,\"chord\":\"B\",\"time_ms\":119860,\"time_ms_arr\":[119860,120480]},{\"beat_count\":4,\"chord\":\"A\",\"time_ms\":121100,\"time_ms_arr\":[121100,121720,122340,122960]},{\"beat_count\":4,\"chord\":\"B\",\"time_ms\":123580,\"time_ms_arr\":[123580,124180,124820,125440]},{\"beat_count\":4,\"chord\":\"A\",\"time_ms\":126040,\"time_ms_arr\":[126040,126660,127300,127900]},{\"beat_count\":4,\"chord\":\"B\",\"time_ms\":128520.00000000001,\"time_ms_arr\":[128520.00000000001,129139.99999999999,129759.99999999999,130380]},{\"beat_count\":4,\"chord\":\"A\",\"time_ms\":131000,\"time_ms_arr\":[131000,131620,132240,132860]},{\"beat_count\":4,\"chord\":\"B\",\"time_ms\":133460,\"time_ms_arr\":[133460,134100,134700,135340]},{\"beat_count\":4,\"chord\":\"A\",\"time_ms\":135940,\"time_ms_arr\":[135940,136560,137180,137800]},{\"beat_count\":4,\"chord\":\"B\",\"time_ms\":138420,\"time_ms_arr\":[138420,139040,139660,140280]},{\"beat_count\":2,\"chord\":\"E\",\"time_ms\":140900,\"time_ms_arr\":[140900,141500]},{\"bar_index\":0,\"beat_index\":0,\"beat_count\":2,\"chord\":\"E\",\"time_ms\":142120,\"time_ms_arr\":[142120,142740],\"passed\":false},{\"beat_count\":4,\"chord\":\"B\",\"time_ms\":143360,\"time_ms_arr\":[143360,143980,144580,145220]},{\"beat_count\":4,\"chord\":\"C#m\",\"time_ms\":145840,\"time_ms_arr\":[145840,146460,147060,147700]},{\"beat_count\":4,\"chord\":\"A\",\"time_ms\":148320,\"time_ms_arr\":[148320,148940,149560,150180]},{\"beat_count\":4,\"chord\":\"E\",\"time_ms\":150780,\"time_ms_arr\":[150780,151400,152040,152640]},{\"beat_count\":4,\"chord\":\"B\",\"time_ms\":153260,\"time_ms_arr\":[153260,153880,154500,155120]},{\"beat_count\":2,\"chord\":\"C#m\",\"time_ms\":155740,\"time_ms_arr\":[155740,156360]},{\"beat_count\":2,\"chord\":\"B\",\"time_ms\":156980,\"time_ms_arr\":[156980,157600]},{\"beat_count\":2,\"chord\":\"A\",\"time_ms\":158200,\"time_ms_arr\":[158200,158840]},{\"beat_count\":2,\"chord\":\"B\",\"time_ms\":159480,\"time_ms_arr\":[159480,160060]},{\"beat_count\":4,\"chord\":\"A\",\"time_ms\":160680,\"time_ms_arr\":[160680,161300,161940,162540]},{\"beat_count\":4,\"chord\":\"B\",\"time_ms\":163160,\"time_ms_arr\":[163160,163760,164420,165020]},{\"beat_count\":4,\"chord\":\"A\",\"time_ms\":165640,\"time_ms_arr\":[165640,166260,166880,167500]},{\"beat_count\":4,\"chord\":\"B\",\"time_ms\":168100,\"time_ms_arr\":[168100,168720,169380,169980]},{\"beat_count\":4,\"chord\":\"A\",\"time_ms\":170580,\"time_ms_arr\":[170580,171220,171840,172440]},{\"beat_count\":4,\"chord\":\"B\",\"time_ms\":173060,\"time_ms_arr\":[173060,173680,174320,174920]},{\"beat_count\":4,\"chord\":\"A\",\"time_ms\":175540,\"time_ms_arr\":[175540,176160,176780,177400]},{\"beat_count\":4,\"chord\":\"B\",\"time_ms\":178020,\"time_ms_arr\":[178020,178620,179260,179860]},{\"beat_count\":4,\"chord\":\"A\",\"time_ms\":180460,\"time_ms_arr\":[180460,181100,181700,182340]},{\"beat_count\":4,\"chord\":\"B\",\"time_ms\":182940,\"time_ms_arr\":[182940,183560,184200,184820]},{\"beat_count\":4,\"chord\":\"A\",\"time_ms\":185440,\"time_ms_arr\":[185440,186040,186680,187280]},{\"beat_count\":4,\"chord\":\"B\",\"time_ms\":187900,\"time_ms_arr\":[187900,188520,189160,189740]},{\"beat_count\":4,\"chord\":\"E\",\"time_ms\":190360,\"time_ms_arr\":[190360,190980,191580,192220]},{\"beat_count\":4,\"chord\":\"B\",\"time_ms\":192820,\"time_ms_arr\":[192820,193440,194080,194680]},{\"beat_count\":4,\"chord\":\"C#m\",\"time_ms\":195300,\"time_ms_arr\":[195300,195920,196560,197160]},{\"beat_count\":2,\"chord\":\"A\",\"time_ms\":197780,\"time_ms_arr\":[197780,198400]},{\"beat_count\":2,\"chord\":\"B\",\"time_ms\":199040,\"time_ms_arr\":[199040,199640]},{\"beat_count\":4,\"chord\":\"E\",\"time_ms\":200280,\"time_ms_arr\":[200280,200880,201540,202120]},{\"beat_count\":4,\"chord\":\"B\",\"time_ms\":202720,\"time_ms_arr\":[202720,203360,204000,204600]},{\"beat_count\":4,\"chord\":\"C#m\",\"time_ms\":205200,\"time_ms_arr\":[205200,205820,206500,207080]},{\"beat_count\":2,\"chord\":\"A\",\"time_ms\":207680,\"time_ms_arr\":[207680,208300]},{\"beat_count\":2,\"chord\":\"B\",\"time_ms\":208980,\"time_ms_arr\":[208980,209560]},{\"beat_count\":4,\"chord\":\"E\",\"time_ms\":210220,\"time_ms_arr\":[210220,210820,211460,212040]}]","lyrics_sync":"[{\"time_ms\":0,\"text\":\"\"},{\"time_ms\":4667,\"text\":\"Hey, hey\"},{\"time_ms\":8883,\"text\":\"Hey, hey, hey, hey\"},{\"time_ms\":12896,\"text\":\"Hey, hey, hey, hey\"},{\"time_ms\":13580,\"text\":\"Your lipstick stains\"},{\"time_ms\":15697,\"text\":\"On the front lobe of my left side brains\"},{\"time_ms\":19680,\"text\":\"I knew I wouldn't forget you\"},{\"time_ms\":23096,\"text\":\"And so I went and let you blow my mind\"},{\"time_ms\":31578,\"text\":\"Your sweet moonbeam\"},{\"time_ms\":34727,\"text\":\"The smell of you in every single dream I dream\"},{\"time_ms\":40460,\"text\":\"I knew when we collided\"},{\"time_ms\":42761,\"text\":\"You're the one I had decided who's one of my kind\"},{\"time_ms\":51528,\"text\":\"Hey, soul sister\"},{\"time_ms\":53994,\"text\":\"Ain't that Mr. Mister on the radio, stereo\"},{\"time_ms\":58994,\"text\":\"The way you move ain't fair you know\"},{\"time_ms\":61595,\"text\":\"Hey, soul sister\"},{\"time_ms\":64060,\"text\":\"I don't wanna miss a single thing you do tonight\"},{\"time_ms\":74145,\"text\":\"Hey, hey\"},{\"time_ms\":77094,\"text\":\"Hey, hey, hey, hey\"},{\"time_ms\":78227,\"text\":\"Hey, hey, hey, hey\"},{\"time_ms\":81694,\"text\":\"Just in time\"},{\"time_ms\":84761,\"text\":\"I'm so glad you have a one track mind like me\"},{\"time_ms\":90261,\"text\":\"You gave my life direction\"},{\"time_ms\":92327,\"text\":\"A game show love connection we can't deny\"},{\"time_ms\":101828,\"text\":\"I'm so obsessed\"},{\"time_ms\":104228,\"text\":\"My heart is bound to beat right out of my untrimmed chest\"},{\"time_ms\":109861,\"text\":\"I believe in you, like a virgin you're madonna\"},{\"time_ms\":114377,\"text\":\"And I'm always gonna wanna blow your mind\"},{\"time_ms\":121628,\"text\":\"\"},{\"time_ms\":122495,\"text\":\"Hey, soul sister\"},{\"time_ms\":123644,\"text\":\"Ain't that Mr. Mister on the radio, stereo\"},{\"time_ms\":128410,\"text\":\"The way you move ain't fair you know\"},{\"time_ms\":131027,\"text\":\"Hey, soul sister\"},{\"time_ms\":133061,\"text\":\"I don't wanna miss a single thing you do tonight\"},{\"time_ms\":141910,\"text\":\"The way you can cut a rug\"},{\"time_ms\":143310,\"text\":\"Watching you is the only drug I need\"},{\"time_ms\":145927,\"text\":\"So gangsta, I'm so thug\"},{\"time_ms\":148227,\"text\":\"You're the only one I'm dreaming of\"},{\"time_ms\":150727,\"text\":\"You see, I can be myself now finally\"},{\"time_ms\":153594,\"text\":\"In fact, there's nothing I can't be\"},{\"time_ms\":156826,\"text\":\"I want the world to see\"},{\"time_ms\":158244,\"text\":\"You'll be with me\"},{\"time_ms\":160660,\"text\":\"Hey, soul sister\"},{\"time_ms\":162726,\"text\":\"Ain't that Mr. Mister on the radio, stereo\"},{\"time_ms\":167794,\"text\":\"The way you move ain't fair you know\"},{\"time_ms\":170461,\"text\":\"Hey, soul sister\"},{\"time_ms\":172693,\"text\":\"I don't wanna miss a single thing you do tonight\"},{\"time_ms\":180310,\"text\":\"Hey, soul sister\"},{\"time_ms\":182610,\"text\":\"I don't wanna miss a single thing you do tonight\"},{\"time_ms\":192710,\"text\":\"Hey, hey\"},{\"time_ms\":193894,\"text\":\"Hey, hey, hey, hey\"},{\"time_ms\":196578,\"text\":\"Hey, hey, hey, hey\"},{\"time_ms\":199444,\"text\":\"Tonight\"},{\"time_ms\":202477,\"text\":\"Hey, hey\"},{\"time_ms\":203777,\"text\":\"Hey, hey, hey, hey\"},{\"time_ms\":206244,\"text\":\"Hey, hey, hey, hey\"},{\"time_ms\":209477,\"text\":\"Tonight\"}]","date_created":"2023-02-01T21:48:52.000Z","date_updated":"2023-02-02T09:25:23.000Z","cook_step":"served","release_year":2009,"region_type":"POP_SONG","artist_name":"Train"}