{"sheet_uid":"q42HXiljFC","title":"꿈에","artist_uid":"GEkBrTeJqs","bpm":136,"capo":0,"origin":2,"video_id":"92nsZ2TDwIk","lyrics_chord":"C     C     C     C      \nC     C     A7     A7      \nDm     Dm     G7     G7      \nC     C     G     G      \nG7     G7     C     C      \n \n  C     C     Em     Em      \n꿈에 어제 꿈에 보았던 \n    A7        A7       Dm     Dm      \n이름모를 너를 나는 못잊어 \n         G     G   C      C      \n본적도 없고 이름도 모르는 \n     Dm     G7       C     C      \n지난 꿈 스쳐간 여인이여 \n     C     C     Em     Em      \n이밤에 곰곰히 생각해보니 \n    A7          A7        Dm     Dm      \n어디선가 본듯한 바로 그 모습 \n         G    G        C     C      \n떠오르는 모습 잊었었던 사람 \n    Dm     G        C     C      \n어느해 만났던 여인이여 \n     Dm      E7      Am     Am      \n어느 가을 만났던 사람이여 \n          Am  Am     Dm    Dm      \n난 눈을 뜨면 꿈에서 깰까봐 \n         E7  E7   Am   Am      \n난 눈 못뜨고 그대를 보네 \n        A   A       Dm       Dm      \n물거품처럼 깨져버린 내 꿈이여 \n      E7   E7  Am     Am      \n오늘밤엔 그대여  와요 \n          Am   Am     Dm      Dm      \n난 눈을 뜨면 사라지는 사람이여 \n          E7   E7  Am    Am      \n난 눈 못뜨고 그대를 또 보네 \n        A   A       Dm       Dm      \n물거품처럼 깨져버린 내 꿈이여 \n       E7  E7  Am   Am      \n오늘 밤에 그대여 와요 \n \nAm     Am     C     C      \nA7     A7     Dm     Dm      \nG     G     C     C      \nG     G     G     G7      \nC     C      \n \n     Dm      E        Am     Am      \n어느 가을 만났던 사람이여 \n          Am   Am   Dm     Dm      \n난 눈을 뜨면 꿈에서 깰까봐 \n          E7  E7  Am   A      \n난 눈 못뜨고 그대를 보네 \n        A   A       Dm       Dm      \n물거품처럼 깨져버린 내 꿈이여 \n      E7  E7  Am    Am      \n오늘밤엔 그대여 와요 \n          Am  Am      Dm     Dm      \n난 눈을 뜨면 사라지는 사람이여 \n          E7  E7  Am     A      \n난 눈 못뜨고 그대를 또 보네 \n        A   A       Dm       Dm      \n물거품처럼 깨져버린 내 꿈이여 \n      E7  E7  Am    Am      \n오늘밤엔 그대여 와요 \n \nF     F     Am     Am      \nE     E     E7     E7      \nAm     Am     Am     A      \nDm     Dm     E     E7      \nAm     Am     Am     Am      \nE     E7     E7     E \n","chord_list":"[{\"beat_count\":4,\"chord\":\"C\",\"time_ms\":660,\"time_ms_arr\":[660,1080,1500,1900]},{\"beat_count\":4,\"chord\":\"C\",\"time_ms\":2320,\"time_ms_arr\":[2320,2780,3220,3640]},{\"beat_count\":4,\"chord\":\"C\",\"time_ms\":4120,\"time_ms_arr\":[4120,4560,4980,5400]},{\"beat_count\":4,\"chord\":\"C\",\"time_ms\":5840,\"time_ms_arr\":[5840,6280,6740,7160]},{\"beat_count\":4,\"chord\":\"C\",\"time_ms\":7620,\"time_ms_arr\":[7620,8060.000000000001,8500,8940]},{\"beat_count\":4,\"chord\":\"C\",\"time_ms\":9360,\"time_ms_arr\":[9360,9820,10280,10680]},{\"beat_count\":4,\"chord\":\"A7\",\"time_ms\":11120,\"time_ms_arr\":[11120,11540,11980,12420]},{\"beat_count\":4,\"chord\":\"A7\",\"time_ms\":12860,\"time_ms_arr\":[12860,13300,13720,14160]},{\"beat_count\":4,\"chord\":\"Dm\",\"time_ms\":14600,\"time_ms_arr\":[14600,15040,15500,15940]},{\"beat_count\":4,\"chord\":\"Dm\",\"time_ms\":16340,\"time_ms_arr\":[16340,16820,17220,17680]},{\"beat_count\":4,\"chord\":\"G7\",\"time_ms\":18100,\"time_ms_arr\":[18100,18540,18980,19420]},{\"beat_count\":4,\"chord\":\"G7\",\"time_ms\":19860,\"time_ms_arr\":[19860,20300,20760,21180]},{\"beat_count\":4,\"chord\":\"C\",\"time_ms\":21600,\"time_ms_arr\":[21600,22020,22460,22880]},{\"beat_count\":4,\"chord\":\"C\",\"time_ms\":23300,\"time_ms_arr\":[23300,23740,24140,24580]},{\"beat_count\":4,\"chord\":\"G\",\"time_ms\":25000,\"time_ms_arr\":[25000,25440,25880,26320]},{\"beat_count\":4,\"chord\":\"G\",\"time_ms\":26740,\"time_ms_arr\":[26740,27200,27640,28080]},{\"beat_count\":4,\"chord\":\"G7\",\"time_ms\":28480,\"time_ms_arr\":[28480,28940,29360,29780]},{\"beat_count\":4,\"chord\":\"G7\",\"time_ms\":30220,\"time_ms_arr\":[30220,30680,31120,31560]},{\"beat_count\":4,\"chord\":\"C\",\"time_ms\":31960,\"time_ms_arr\":[31960,32400,32840,33260]},{\"beat_count\":4,\"chord\":\"C\",\"time_ms\":33740,\"time_ms_arr\":[33740,34160,34600,35040]},{\"beat_count\":4,\"chord\":\"C\",\"time_ms\":35480,\"time_ms_arr\":[35480,35900,36360,36780]},{\"beat_count\":4,\"chord\":\"C\",\"time_ms\":37260,\"time_ms_arr\":[37260,37660,38100,38540]},{\"beat_count\":4,\"chord\":\"Em\",\"time_ms\":38940,\"time_ms_arr\":[38940,39380,39800,40200]},{\"beat_count\":4,\"chord\":\"Em\",\"time_ms\":40660,\"time_ms_arr\":[40660,41060,41500,41920]},{\"beat_count\":4,\"chord\":\"A7\",\"time_ms\":42360,\"time_ms_arr\":[42360,42760,43220,43660]},{\"beat_count\":4,\"chord\":\"A7\",\"time_ms\":44080,\"time_ms_arr\":[44080,44560,44980,45400]},{\"beat_count\":4,\"chord\":\"Dm\",\"time_ms\":45860,\"time_ms_arr\":[45860,46280,46740,47180]},{\"beat_count\":4,\"chord\":\"Dm\",\"time_ms\":47600,\"time_ms_arr\":[47600,48060,48480,48880]},{\"beat_count\":4,\"chord\":\"G\",\"time_ms\":49320,\"time_ms_arr\":[49320,49760,50220,50640]},{\"beat_count\":4,\"chord\":\"G\",\"time_ms\":51080,\"time_ms_arr\":[51080,51520,51940,52360]},{\"beat_count\":4,\"chord\":\"C\",\"time_ms\":52780,\"time_ms_arr\":[52780,53240,53680,54100]},{\"beat_count\":4,\"chord\":\"C\",\"time_ms\":54520,\"time_ms_arr\":[54520,54960,55400,55860]},{\"beat_count\":4,\"chord\":\"Dm\",\"time_ms\":56300,\"time_ms_arr\":[56300,56760,57180,57580]},{\"beat_count\":4,\"chord\":\"G7\",\"time_ms\":58020,\"time_ms_arr\":[58020,58480,58920,59340]},{\"beat_count\":4,\"chord\":\"C\",\"time_ms\":59780,\"time_ms_arr\":[59780,60220,60660,61080]},{\"beat_count\":4,\"chord\":\"C\",\"time_ms\":61520,\"time_ms_arr\":[61520,62000,62400,62820]},{\"beat_count\":4,\"chord\":\"C\",\"time_ms\":63260,\"time_ms_arr\":[63260,63700,64099.99999999999,64500]},{\"beat_count\":4,\"chord\":\"C\",\"time_ms\":64959.99999999999,\"time_ms_arr\":[64959.99999999999,65379.99999999999,65820,66240]},{\"beat_count\":4,\"chord\":\"Em\",\"time_ms\":66700,\"time_ms_arr\":[66700,67140,67580,67980]},{\"beat_count\":4,\"chord\":\"Em\",\"time_ms\":68420,\"time_ms_arr\":[68420,68880,69340,69740]},{\"beat_count\":4,\"chord\":\"A7\",\"time_ms\":70180,\"time_ms_arr\":[70180,70640,71060,71480]},{\"beat_count\":4,\"chord\":\"A7\",\"time_ms\":71900,\"time_ms_arr\":[71900,72340,72740,73200]},{\"beat_count\":4,\"chord\":\"Dm\",\"time_ms\":73640,\"time_ms_arr\":[73640,74080,74500,74920]},{\"beat_count\":4,\"chord\":\"Dm\",\"time_ms\":75380,\"time_ms_arr\":[75380,75840,76260,76700]},{\"beat_count\":4,\"chord\":\"G\",\"time_ms\":77160,\"time_ms_arr\":[77160,77580,78000,78440]},{\"beat_count\":4,\"chord\":\"G\",\"time_ms\":78880,\"time_ms_arr\":[78880,79280,79740,80160]},{\"beat_count\":4,\"chord\":\"C\",\"time_ms\":80620,\"time_ms_arr\":[80620,81040,81500,81900]},{\"beat_count\":4,\"chord\":\"C\",\"time_ms\":82340,\"time_ms_arr\":[82340,82820,83260,83700]},{\"beat_count\":4,\"chord\":\"Dm\",\"time_ms\":84120,\"time_ms_arr\":[84120,84540,85000,85420]},{\"beat_count\":4,\"chord\":\"G\",\"time_ms\":85880,\"time_ms_arr\":[85880,86300,86760,87160]},{\"beat_count\":4,\"chord\":\"C\",\"time_ms\":87580,\"time_ms_arr\":[87580,88020,88460,88860]},{\"beat_count\":4,\"chord\":\"C\",\"time_ms\":89280,\"time_ms_arr\":[89280,89740,90180,90620]},{\"beat_count\":4,\"chord\":\"Dm\",\"time_ms\":91060,\"time_ms_arr\":[91060,91500,91920,92360]},{\"beat_count\":4,\"chord\":\"E7\",\"time_ms\":92800,\"time_ms_arr\":[92800,93220,93640,94080]},{\"beat_count\":4,\"chord\":\"Am\",\"time_ms\":94520,\"time_ms_arr\":[94520,94940,95380,95800]},{\"beat_count\":4,\"chord\":\"Am\",\"time_ms\":96240,\"time_ms_arr\":[96240,96660,97100,97520]},{\"beat_count\":4,\"chord\":\"Am\",\"time_ms\":97960,\"time_ms_arr\":[97960,98400,98840,99260]},{\"beat_count\":4,\"chord\":\"Am\",\"time_ms\":99720,\"time_ms_arr\":[99720,100100,100560,101020]},{\"beat_count\":4,\"chord\":\"Dm\",\"time_ms\":101440,\"time_ms_arr\":[101440,101880,102340,102760]},{\"beat_count\":4,\"chord\":\"Dm\",\"time_ms\":103220,\"time_ms_arr\":[103220,103640,104080,104500]},{\"beat_count\":4,\"chord\":\"E7\",\"time_ms\":104940,\"time_ms_arr\":[104940,105360,105800,106240]},{\"beat_count\":4,\"chord\":\"E7\",\"time_ms\":106680,\"time_ms_arr\":[106680,107100,107540,107960]},{\"beat_count\":4,\"chord\":\"Am\",\"time_ms\":108400,\"time_ms_arr\":[108400,108840,109260,109700]},{\"beat_count\":4,\"chord\":\"Am\",\"time_ms\":110140,\"time_ms_arr\":[110140,110560,111000,111440]},{\"beat_count\":4,\"chord\":\"A\",\"time_ms\":111880,\"time_ms_arr\":[111880,112320,112760,113180]},{\"beat_count\":4,\"chord\":\"A\",\"time_ms\":113640,\"time_ms_arr\":[113640,114060,114500,114940]},{\"beat_count\":4,\"chord\":\"Dm\",\"time_ms\":115360,\"time_ms_arr\":[115360,115800,116240,116680]},{\"beat_count\":4,\"chord\":\"Dm\",\"time_ms\":117120,\"time_ms_arr\":[117120,117540,118000,118420]},{\"beat_count\":4,\"chord\":\"E7\",\"time_ms\":118860,\"time_ms_arr\":[118860,119300,119720,120160]},{\"beat_count\":4,\"chord\":\"E7\",\"time_ms\":120600,\"time_ms_arr\":[120600,121000,121440,121860]},{\"beat_count\":4,\"chord\":\"Am\",\"time_ms\":122300,\"time_ms_arr\":[122300,122720,123160,123580]},{\"beat_count\":4,\"chord\":\"Am\",\"time_ms\":124020,\"time_ms_arr\":[124020,124440,124860,125300]},{\"beat_count\":4,\"chord\":\"Am\",\"time_ms\":125740,\"time_ms_arr\":[125740,126180,126620,127040]},{\"beat_count\":4,\"chord\":\"Am\",\"time_ms\":127500,\"time_ms_arr\":[127500,127940,128360.00000000001,128800.00000000001]},{\"beat_count\":4,\"chord\":\"Dm\",\"time_ms\":129240.00000000001,\"time_ms_arr\":[129240.00000000001,129680,130120,130539.99999999999]},{\"beat_count\":4,\"chord\":\"Dm\",\"time_ms\":131000,\"time_ms_arr\":[131000,131420,131860,132280]},{\"beat_count\":4,\"chord\":\"E7\",\"time_ms\":132720,\"time_ms_arr\":[132720,133160,133600,134040]},{\"beat_count\":4,\"chord\":\"E7\",\"time_ms\":134480,\"time_ms_arr\":[134480,134880,135320,135740]},{\"beat_count\":4,\"chord\":\"Am\",\"time_ms\":136180,\"time_ms_arr\":[136180,136620,137040,137480]},{\"beat_count\":4,\"chord\":\"Am\",\"time_ms\":137920,\"time_ms_arr\":[137920,138340,138780,139200]},{\"beat_count\":4,\"chord\":\"A\",\"time_ms\":139620,\"time_ms_arr\":[139620,140080,140520,140940]},{\"beat_count\":4,\"chord\":\"A\",\"time_ms\":141380,\"time_ms_arr\":[141380,141820,142260,142680]},{\"beat_count\":4,\"chord\":\"Dm\",\"time_ms\":143120,\"time_ms_arr\":[143120,143560,144000,144440]},{\"beat_count\":4,\"chord\":\"Dm\",\"time_ms\":144860,\"time_ms_arr\":[144860,145300,145740,146160]},{\"beat_count\":4,\"chord\":\"E7\",\"time_ms\":146600,\"time_ms_arr\":[146600,147040,147480,147920]},{\"beat_count\":4,\"chord\":\"E7\",\"time_ms\":148340,\"time_ms_arr\":[148340,148780,149220,149660]},{\"beat_count\":4,\"chord\":\"Am\",\"time_ms\":150100,\"time_ms_arr\":[150100,150520,150960,151400]},{\"beat_count\":4,\"chord\":\"Am\",\"time_ms\":151840,\"time_ms_arr\":[151840,152260,152720,153160]},{\"beat_count\":4,\"chord\":\"Am\",\"time_ms\":153580,\"time_ms_arr\":[153580,154000,154440,154880]},{\"beat_count\":4,\"chord\":\"Am\",\"time_ms\":155320,\"time_ms_arr\":[155320,155760,156200,156600]},{\"beat_count\":4,\"chord\":\"C\",\"time_ms\":157060,\"time_ms_arr\":[157060,157500,157920,158360]},{\"beat_count\":4,\"chord\":\"C\",\"time_ms\":158820,\"time_ms_arr\":[158820,159260,159680,160120]},{\"beat_count\":4,\"chord\":\"A7\",\"time_ms\":160540,\"time_ms_arr\":[160540,160980,161420,161860]},{\"beat_count\":4,\"chord\":\"A7\",\"time_ms\":162300,\"time_ms_arr\":[162300,162720,163160,163580]},{\"beat_count\":4,\"chord\":\"Dm\",\"time_ms\":164020,\"time_ms_arr\":[164020,164460,164900,165320]},{\"beat_count\":4,\"chord\":\"Dm\",\"time_ms\":165760,\"time_ms_arr\":[165760,166200,166640,167060]},{\"beat_count\":4,\"chord\":\"G\",\"time_ms\":167500,\"time_ms_arr\":[167500,167940,168360,168800]},{\"beat_count\":4,\"chord\":\"G\",\"time_ms\":169240,\"time_ms_arr\":[169240,169680,170100,170540]},{\"beat_count\":4,\"chord\":\"C\",\"time_ms\":170960,\"time_ms_arr\":[170960,171400,171820,172260]},{\"beat_count\":4,\"chord\":\"C\",\"time_ms\":172700,\"time_ms_arr\":[172700,173140,173580,174000]},{\"beat_count\":4,\"chord\":\"G\",\"time_ms\":174440,\"time_ms_arr\":[174440,174880,175300,175740]},{\"beat_count\":4,\"chord\":\"G\",\"time_ms\":176180,\"time_ms_arr\":[176180,176620,177040,177460]},{\"beat_count\":4,\"chord\":\"G\",\"time_ms\":177900,\"time_ms_arr\":[177900,178340,178760,179200]},{\"beat_count\":4,\"chord\":\"G7\",\"time_ms\":179640,\"time_ms_arr\":[179640,180060,180520,180940]},{\"beat_count\":4,\"chord\":\"C\",\"time_ms\":181380,\"time_ms_arr\":[181380,181820,182240,182680]},{\"beat_count\":4,\"chord\":\"C\",\"time_ms\":183100,\"time_ms_arr\":[183100,183540,183980,184420]},{\"beat_count\":4,\"chord\":\"Dm\",\"time_ms\":184860,\"time_ms_arr\":[184860,185300,185740,186180]},{\"beat_count\":4,\"chord\":\"E\",\"time_ms\":186640,\"time_ms_arr\":[186640,187040,187480,187900]},{\"beat_count\":4,\"chord\":\"Am\",\"time_ms\":188340,\"time_ms_arr\":[188340,188780,189200,189640]},{\"beat_count\":4,\"chord\":\"Am\",\"time_ms\":190100,\"time_ms_arr\":[190100,190500,190940,191360]},{\"beat_count\":4,\"chord\":\"Am\",\"time_ms\":191800,\"time_ms_arr\":[191800,192240,192680,193120]},{\"beat_count\":4,\"chord\":\"Am\",\"time_ms\":193580,\"time_ms_arr\":[193580,194000,194440,194880]},{\"beat_count\":4,\"chord\":\"Dm\",\"time_ms\":195300,\"time_ms_arr\":[195300,195740,196180,196620]},{\"beat_count\":4,\"chord\":\"Dm\",\"time_ms\":197060,\"time_ms_arr\":[197060,197480,197920,198340]},{\"beat_count\":4,\"chord\":\"E7\",\"time_ms\":198780,\"time_ms_arr\":[198780,199220,199660,200100]},{\"beat_count\":4,\"chord\":\"E7\",\"time_ms\":200520,\"time_ms_arr\":[200520,200960,201400,201840]},{\"beat_count\":4,\"chord\":\"Am\",\"time_ms\":202260,\"time_ms_arr\":[202260,202700,203140,203560]},{\"beat_count\":4,\"chord\":\"A\",\"time_ms\":204020,\"time_ms_arr\":[204020,204420,204860,205300]},{\"beat_count\":4,\"chord\":\"A\",\"time_ms\":205720,\"time_ms_arr\":[205720,206160,206600,207020]},{\"beat_count\":4,\"chord\":\"A\",\"time_ms\":207460,\"time_ms_arr\":[207460,207900,208340,208760]},{\"beat_count\":4,\"chord\":\"Dm\",\"time_ms\":209200,\"time_ms_arr\":[209200,209640,210060,210500]},{\"beat_count\":4,\"chord\":\"Dm\",\"time_ms\":210940,\"time_ms_arr\":[210940,211360,211800,212220]},{\"beat_count\":4,\"chord\":\"E7\",\"time_ms\":212660,\"time_ms_arr\":[212660,213100,213540,213960]},{\"beat_count\":4,\"chord\":\"E7\",\"time_ms\":214420,\"time_ms_arr\":[214420,214840,215260,215700]},{\"beat_count\":4,\"chord\":\"Am\",\"time_ms\":216140,\"time_ms_arr\":[216140,216560,217000,217420]},{\"beat_count\":4,\"chord\":\"Am\",\"time_ms\":217880,\"time_ms_arr\":[217880,218280,218720,219140]},{\"beat_count\":4,\"chord\":\"Am\",\"time_ms\":219580,\"time_ms_arr\":[219580,220020,220460,220900]},{\"beat_count\":4,\"chord\":\"Am\",\"time_ms\":221340,\"time_ms_arr\":[221340,221780,222200,222640]},{\"beat_count\":4,\"chord\":\"Dm\",\"time_ms\":223060,\"time_ms_arr\":[223060,223500,223940,224360]},{\"beat_count\":4,\"chord\":\"Dm\",\"time_ms\":224820,\"time_ms_arr\":[224820,225260,225700,226120]},{\"beat_count\":4,\"chord\":\"E7\",\"time_ms\":226560,\"time_ms_arr\":[226560,227000,227440,227860]},{\"beat_count\":4,\"chord\":\"E7\",\"time_ms\":228320,\"time_ms_arr\":[228320,228740,229160,229600]},{\"beat_count\":4,\"chord\":\"Am\",\"time_ms\":230020,\"time_ms_arr\":[230020,230460,230900,231320]},{\"beat_count\":4,\"chord\":\"A\",\"time_ms\":231760,\"time_ms_arr\":[231760,232180,232620,233060]},{\"beat_count\":4,\"chord\":\"A\",\"time_ms\":233480,\"time_ms_arr\":[233480,233920,234380,234800]},{\"beat_count\":4,\"chord\":\"A\",\"time_ms\":235240,\"time_ms_arr\":[235240,235680,236100,236520]},{\"beat_count\":4,\"chord\":\"Dm\",\"time_ms\":236980,\"time_ms_arr\":[236980,237400,237840,238280]},{\"beat_count\":4,\"chord\":\"Dm\",\"time_ms\":238740,\"time_ms_arr\":[238740,239160,239600,240040]},{\"beat_count\":4,\"chord\":\"E7\",\"time_ms\":240480,\"time_ms_arr\":[240480,240920,241340,241780]},{\"beat_count\":4,\"chord\":\"E7\",\"time_ms\":242240,\"time_ms_arr\":[242240,242660,243100,243540]},{\"beat_count\":4,\"chord\":\"Am\",\"time_ms\":243960,\"time_ms_arr\":[243960,244400,244840,245260]},{\"beat_count\":4,\"chord\":\"Am\",\"time_ms\":245720,\"time_ms_arr\":[245720,246120,246560,246980]},{\"beat_count\":4,\"chord\":\"F\",\"time_ms\":247420,\"time_ms_arr\":[247420,247860,248280,248720]},{\"beat_count\":4,\"chord\":\"F\",\"time_ms\":249160,\"time_ms_arr\":[249160,249560,250020,250440]},{\"beat_count\":4,\"chord\":\"Am\",\"time_ms\":250860,\"time_ms_arr\":[250860,251320,251740,252180]},{\"beat_count\":4,\"chord\":\"Am\",\"time_ms\":252660,\"time_ms_arr\":[252660,253060,253500,253940]},{\"beat_count\":4,\"chord\":\"E\",\"time_ms\":254380,\"time_ms_arr\":[254380,254800,255240,255680]},{\"beat_count\":4,\"chord\":\"E\",\"time_ms\":256140,\"time_ms_arr\":[256140,256540.00000000003,256980.00000000003,257420.00000000003]},{\"beat_count\":4,\"chord\":\"E7\",\"time_ms\":257860,\"time_ms_arr\":[257860,258300,258740,259160.00000000003]},{\"beat_count\":4,\"chord\":\"E7\",\"time_ms\":259600.00000000003,\"time_ms_arr\":[259600.00000000003,260040.00000000003,260480.00000000003,260920.00000000003]},{\"beat_count\":4,\"chord\":\"Am\",\"time_ms\":261360,\"time_ms_arr\":[261360,261800,262240,262680]},{\"beat_count\":4,\"chord\":\"Am\",\"time_ms\":263140,\"time_ms_arr\":[263140,263540,263980,264400]},{\"beat_count\":4,\"chord\":\"Am\",\"time_ms\":264840,\"time_ms_arr\":[264840,265280,265720,266160]},{\"beat_count\":4,\"chord\":\"A\",\"time_ms\":266600,\"time_ms_arr\":[266600,267020,267460,267880]},{\"beat_count\":4,\"chord\":\"Dm\",\"time_ms\":268320,\"time_ms_arr\":[268320,268760,269180,269620]},{\"beat_count\":4,\"chord\":\"Dm\",\"time_ms\":270060,\"time_ms_arr\":[270060,270480,270920,271360]},{\"beat_count\":4,\"chord\":\"E\",\"time_ms\":271780,\"time_ms_arr\":[271780,272220,272660,273080]},{\"beat_count\":4,\"chord\":\"E7\",\"time_ms\":273520,\"time_ms_arr\":[273520,273960,274380,274820]},{\"beat_count\":4,\"chord\":\"Am\",\"time_ms\":275260,\"time_ms_arr\":[275260,275700,276140,276580]},{\"beat_count\":4,\"chord\":\"Am\",\"time_ms\":277040,\"time_ms_arr\":[277040,277440,277880,278300]},{\"beat_count\":4,\"chord\":\"Am\",\"time_ms\":278740,\"time_ms_arr\":[278740,279180,279600,280040]},{\"beat_count\":4,\"chord\":\"Am\",\"time_ms\":280480,\"time_ms_arr\":[280480,280900,281360,281800]},{\"beat_count\":4,\"chord\":\"E\",\"time_ms\":282220,\"time_ms_arr\":[282220,282660,283100,283540]},{\"beat_count\":4,\"chord\":\"E7\",\"time_ms\":283980,\"time_ms_arr\":[283980,284400,284840,285240]},{\"beat_count\":4,\"chord\":\"E7\",\"time_ms\":285700,\"time_ms_arr\":[285700,286120,286560,287000]},{\"beat_count\":4,\"chord\":\"E\",\"time_ms\":287440,\"time_ms_arr\":[287440,287860,288300,288720]}]","lyrics_sync":"null","date_created":"2022-11-10T12:00:37.000Z","date_updated":"2022-11-19T06:26:11.000Z","cook_step":"served","artist_name":"조덕배"}