{"sheet_uid":"ts08SasqZx","title":"내 그리운 나라","artist_uid":"1pjpMHEAAG","bpm":67,"capo":0,"origin":0,"video_id":"W5zE_Iy-2V4","lyrics_chord":"G     \nG           G    D              G     \n내 그리운 나라 울다 지쳐 잠이 들면\nG           G     D      G     \n내 그리운 나라 갈 수 있을까\n  D              G    D       G     \n길을 잃은 아이 처럼 울고 싶은 밤\n      C         G      D      G     \n길바닥에 주저 앉아 어둠을 붙안고\n      C    G    D      G     \n허공에선 슬픈 나의 그림자\nG           G    D              G     \n내 그리운 나라 울다 지쳐 잠이 들면\nG           G     D      G     \n내 그리운 나라 갈 수 있을까\n\nG     G     D     G     \nG     G     D     G     \n\n      C         G      D      G     \n길바닥에 주저 앉아 어둠을 붙안고\n      C    G    D      G     \n허공에선 슬픈 나의 그림자\nG           G    D              G     \n내 그리운 나라 울다 지쳐 잠이 들면\nG           G     D      G     \n내 그리운 나라 갈 수 있을까\n\nG     G     D     G     \nG     G     D     D     G\n\n","chord_list":"[{\"beat_count\":4,\"chord\":\"G\",\"time_ms\":13250,\"time_ms_arr\":[13250,14180,15120,16059.999999999998]},{\"beat_count\":4,\"chord\":\"G\",\"time_ms\":17000,\"time_ms_arr\":[17000,17940,18880,19780]},{\"beat_count\":4,\"chord\":\"G\",\"time_ms\":20680,\"time_ms_arr\":[20680,21580,22480,23380]},{\"beat_count\":4,\"chord\":\"D\",\"time_ms\":24280,\"time_ms_arr\":[24280,25180,26080,26980]},{\"beat_count\":4,\"chord\":\"G\",\"time_ms\":27900,\"time_ms_arr\":[27900,28820,29740,30660]},{\"beat_count\":4,\"chord\":\"G\",\"time_ms\":31580,\"time_ms_arr\":[31580,32479.999999999996,33380,34280]},{\"beat_count\":4,\"chord\":\"G\",\"time_ms\":35180,\"time_ms_arr\":[35180,36080,36980,37880]},{\"beat_count\":4,\"chord\":\"D\",\"time_ms\":38780,\"time_ms_arr\":[38780,39680,40580,41480]},{\"beat_count\":4,\"chord\":\"G\",\"time_ms\":42380,\"time_ms_arr\":[42380,43280,44200,45120]},{\"beat_count\":4,\"chord\":\"D\",\"time_ms\":46040,\"time_ms_arr\":[46040,46940,47840,48740]},{\"beat_count\":4,\"chord\":\"G\",\"time_ms\":49640,\"time_ms_arr\":[49640,50520,51400,52300]},{\"beat_count\":4,\"chord\":\"D\",\"time_ms\":53200,\"time_ms_arr\":[53200,54100,55000,55900]},{\"beat_count\":4,\"chord\":\"G\",\"time_ms\":56780,\"time_ms_arr\":[56780,57660,58540,59440]},{\"beat_count\":4,\"chord\":\"C\",\"time_ms\":60340,\"time_ms_arr\":[60340,61240,62140,63040]},{\"beat_count\":4,\"chord\":\"G\",\"time_ms\":63940,\"time_ms_arr\":[63940,64840,65740,66640]},{\"beat_count\":4,\"chord\":\"D\",\"time_ms\":67540,\"time_ms_arr\":[67540,68440,69340,70240]},{\"beat_count\":4,\"chord\":\"G\",\"time_ms\":71140,\"time_ms_arr\":[71140,72020,72900,73780]},{\"beat_count\":4,\"chord\":\"C\",\"time_ms\":74660,\"time_ms_arr\":[74660,75540,76420,77300]},{\"beat_count\":4,\"chord\":\"G\",\"time_ms\":78200,\"time_ms_arr\":[78200,79100,80000,80900]},{\"beat_count\":4,\"chord\":\"D\",\"time_ms\":81800,\"time_ms_arr\":[81800,82700,83580,84460]},{\"beat_count\":4,\"chord\":\"G\",\"time_ms\":85340,\"time_ms_arr\":[85340,86220,87100,87980]},{\"beat_count\":4,\"chord\":\"G\",\"time_ms\":88880,\"time_ms_arr\":[88880,89780,90680,91560]},{\"beat_count\":4,\"chord\":\"G\",\"time_ms\":92440,\"time_ms_arr\":[92440,93320,94200,95080]},{\"beat_count\":4,\"chord\":\"D\",\"time_ms\":95980,\"time_ms_arr\":[95980,96880,97760,98660]},{\"beat_count\":4,\"chord\":\"G\",\"time_ms\":99540,\"time_ms_arr\":[99540,100420,101300,102180]},{\"beat_count\":4,\"chord\":\"G\",\"time_ms\":103080,\"time_ms_arr\":[103080,103980,104860,105740]},{\"beat_count\":4,\"chord\":\"G\",\"time_ms\":106620,\"time_ms_arr\":[106620,107500,108380,109260]},{\"beat_count\":4,\"chord\":\"D\",\"time_ms\":110140,\"time_ms_arr\":[110140,111020,111900,112780]},{\"beat_count\":4,\"chord\":\"G\",\"time_ms\":113660,\"time_ms_arr\":[113660,114520,115380,116260]},{\"beat_count\":4,\"chord\":\"G\",\"time_ms\":117140,\"time_ms_arr\":[117140,118040,118940,119840]},{\"beat_count\":4,\"chord\":\"G\",\"time_ms\":120740,\"time_ms_arr\":[120740,121620,122500,123380]},{\"beat_count\":4,\"chord\":\"D\",\"time_ms\":124280,\"time_ms_arr\":[124280,125160,126040,126940]},{\"beat_count\":4,\"chord\":\"G\",\"time_ms\":127840,\"time_ms_arr\":[127840,128740.00000000001,129620,130500]},{\"beat_count\":4,\"chord\":\"G\",\"time_ms\":131380,\"time_ms_arr\":[131380,132260,133140,134040]},{\"beat_count\":4,\"chord\":\"G\",\"time_ms\":134940,\"time_ms_arr\":[134940,135820,136700,137580]},{\"beat_count\":4,\"chord\":\"D\",\"time_ms\":138460,\"time_ms_arr\":[138460,139340,140240,141140]},{\"beat_count\":4,\"chord\":\"G\",\"time_ms\":142040,\"time_ms_arr\":[142040,142920,143800,144680]},{\"beat_count\":4,\"chord\":\"C\",\"time_ms\":145580,\"time_ms_arr\":[145580,146480,147380,148280]},{\"beat_count\":4,\"chord\":\"G\",\"time_ms\":149180,\"time_ms_arr\":[149180,150060,150940,151820]},{\"beat_count\":4,\"chord\":\"D\",\"time_ms\":152700,\"time_ms_arr\":[152700,153580,154480,155380]},{\"beat_count\":4,\"chord\":\"G\",\"time_ms\":156260,\"time_ms_arr\":[156260,157140,158020,158900]},{\"beat_count\":4,\"chord\":\"C\",\"time_ms\":159800,\"time_ms_arr\":[159800,160700,161600,162500]},{\"beat_count\":4,\"chord\":\"G\",\"time_ms\":163400,\"time_ms_arr\":[163400,164300,165200,166100]},{\"beat_count\":4,\"chord\":\"D\",\"time_ms\":167000,\"time_ms_arr\":[167000,167880,168760,169640]},{\"beat_count\":4,\"chord\":\"G\",\"time_ms\":170520,\"time_ms_arr\":[170520,171400,172280,173160]},{\"beat_count\":4,\"chord\":\"G\",\"time_ms\":174040,\"time_ms_arr\":[174040,174940,175840,176740]},{\"beat_count\":4,\"chord\":\"G\",\"time_ms\":177620,\"time_ms_arr\":[177620,178500,179380,180260]},{\"beat_count\":4,\"chord\":\"D\",\"time_ms\":181140,\"time_ms_arr\":[181140,182020,182900,183780]},{\"beat_count\":4,\"chord\":\"G\",\"time_ms\":184680,\"time_ms_arr\":[184680,185560,186440,187320]},{\"beat_count\":4,\"chord\":\"G\",\"time_ms\":188200,\"time_ms_arr\":[188200,189080,189960,190860]},{\"beat_count\":4,\"chord\":\"G\",\"time_ms\":191760,\"time_ms_arr\":[191760,192640,193520,194400]},{\"beat_count\":4,\"chord\":\"D\",\"time_ms\":195280,\"time_ms_arr\":[195280,196160,197040,197920]},{\"beat_count\":4,\"chord\":\"G\",\"time_ms\":198800,\"time_ms_arr\":[198800,199680,200560,201420]},{\"beat_count\":4,\"chord\":\"G\",\"time_ms\":202300,\"time_ms_arr\":[202300,203200,204100,204980]},{\"beat_count\":4,\"chord\":\"G\",\"time_ms\":205860,\"time_ms_arr\":[205860,206740,207620,208500]},{\"beat_count\":4,\"chord\":\"D\",\"time_ms\":209380,\"time_ms_arr\":[209380,210260,211160,212060]},{\"beat_count\":4,\"chord\":\"G\",\"time_ms\":212960,\"time_ms_arr\":[212960,213840,214720,215600]},{\"beat_count\":4,\"chord\":\"G\",\"time_ms\":216500,\"time_ms_arr\":[216500,217400,218300,219200]},{\"beat_count\":4,\"chord\":\"G\",\"time_ms\":220100,\"time_ms_arr\":[220100,220980,221860,222740]},{\"beat_count\":4,\"chord\":\"D\",\"time_ms\":223620,\"time_ms_arr\":[223620,224540,225480,226440]},{\"beat_count\":4,\"chord\":\"D\",\"time_ms\":227510,\"time_ms_arr\":[227510,228610,229710,230810]},{\"beat_count\":4,\"chord\":\"G\",\"time_ms\":231910,\"time_ms_arr\":[231910,232970,234030,235090]}]","lyrics_sync":"[{\"time_ms\":0,\"text\":\"\"},{\"time_ms\":18179,\"text\":\"내 그리운 나라 울다 지쳐 잠이 들면\"},{\"time_ms\":31044,\"text\":\"내 그리운 나라 갈 수 있을까\"},{\"time_ms\":45761,\"text\":\"내 그리운 나라 울다 지쳐 잠이 들면\"},{\"time_ms\":52078,\"text\":\"내 그리운 나라 갈 수 있을까\"},{\"time_ms\":52678,\"text\":\"길을 잃은 아이처럼 울고 싶은 밤\"},{\"time_ms\":59828,\"text\":\"길바닥에 주저 앉아 어둠을 붙안고\"},{\"time_ms\":74383,\"text\":\"허공에선 슬픈 나의 그림자\"},{\"time_ms\":90842,\"text\":\"\"},{\"time_ms\":102714,\"text\":\"\"},{\"time_ms\":118860,\"text\":\"\"},{\"time_ms\":132609,\"text\":\"\"},{\"time_ms\":145029,\"text\":\"길을 잃은 아이처럼 울고 싶은 밤\"},{\"time_ms\":146845,\"text\":\"길바닥에 주저 앉아 어둠을 붙안고\"},{\"time_ms\":158877,\"text\":\"허공에선 슬픈 나의 그림자\"},{\"time_ms\":173660,\"text\":\"내 그리운 나라 울다 지쳐 잠이 들면\"},{\"time_ms\":188061,\"text\":\"내 그리운 나라 갈 수 있을까\"},{\"time_ms\":201917,\"text\":\"\"},{\"time_ms\":216259,\"text\":\"\"}]","date_created":"2023-01-06T10:55:05.000Z","date_updated":"2023-01-06T13:10:41.000Z","cook_step":"served","release_year":1987,"region_type":"KPOP","artist_name":"임지훈"}