{"sheet_uid":"y62AoVwCUD","title":"풀잎사랑","artist_uid":"xSvC4cxdrp","bpm":125,"capo":0,"origin":0,"video_id":"ptRoCD-zuJ8","lyrics_chord":"G     Am     D     G     \nG     Am     D     G     \n\nG             Am     \n싱그러운 아침 햇살이 \nD                G     \n풀잎에 맺힌 이슬 비칠때면\nG             Am     \n부시시 잠깨인 얼굴로 \nD                G     \n해맑은 그대 모습 보았어요\n\nG             Am     \n푸르른 날에는 더욱 더 \nD             G     \n사랑하는 마음 알았지만\nG             Am     \n햇살에 눈부신 이슬은 \nD                G     \n차라리 눈을 감고 말았어요\n\n       D     D     \n그대는 풀잎 \n     G     G     \n나는 이슬 \n       D     D     \n그대는 이슬 \n     G     G     \n나는 햇살\n\n    C     C     \n사랑해 \n    G     G     \n그대만을 \n    D     D     \n우리는 \n     G     G     \n풀잎 사랑\n\n       D         D     \n그대는 풀잎 풀잎 풀잎 \n     G         G     \n나는 이슬 이슬 이슬\n       D         D     \n그대는 이슬 이슬 이슬 \n     G         G     \n나는 햇살 햇살 햇살\n\n    C     C     \n사랑해 \n    G     G     \n그대만을 \n    D     D     \n우리는 \n     G     G     \n풀잎 사랑\n\nG     Am     D     G     \nG     Am     D     G     \n\nG              Am     \n빛나던 노을 빛 사랑도 \nD               G     \n칸칸이 쓰러지고 말았지만\nG           Am     \n어둠을 홀로 밝히는\nD              G     \n나의 사랑 변함 없어요\n\n       D     D     \n그대는 풀잎\n     G     G     \n나는 이슬\n       D     D     \n그대는 이슬\n     G     G     \n나는 햇살\n\n    C     C     \n사랑해 \n    G     G     \n그대만을\n    D     D     \n우리는 \n     G     G     \n풀잎 사랑\n\n       D         D     \n그대는 풀잎 풀잎 풀잎\n     G         G     \n나는 이슬 이슬 이슬\n       D         D     \n그대는 이슬 이슬 이슬\n     G         G     \n나는 햇살 햇살 햇살\n\n    C     C     \n사랑해 \n     G     G     \n그대 만을\n    D     D     \n우리는 \n     G     G     \n풀잎 사랑\n    D     D     \n우리는 \n     G     G     \n풀잎 사랑\n    D     D     \n우리는 \n     G     G     \n풀잎 사랑\n\nG     Am     D     G     \nG     Am     D     G     \nG     Am     D     G     \nG     Am\n\n","chord_list":"[{\"beat_count\":4,\"chord\":\"G\",\"time_ms\":2580,\"time_ms_arr\":[2580,3040,3520,4000]},{\"beat_count\":4,\"chord\":\"Am\",\"time_ms\":4460,\"time_ms_arr\":[4460,4940,5400,5880]},{\"beat_count\":4,\"chord\":\"D\",\"time_ms\":6360,\"time_ms_arr\":[6360,6820,7300,7760]},{\"beat_count\":4,\"chord\":\"G\",\"time_ms\":8240,\"time_ms_arr\":[8240,8720,9200,9660]},{\"beat_count\":4,\"chord\":\"G\",\"time_ms\":10140,\"time_ms_arr\":[10140,10600,11080,11540]},{\"beat_count\":4,\"chord\":\"Am\",\"time_ms\":12020,\"time_ms_arr\":[12020,12480,12960,13440]},{\"beat_count\":4,\"chord\":\"D\",\"time_ms\":13900,\"time_ms_arr\":[13900,14380,14860,15320]},{\"beat_count\":4,\"chord\":\"G\",\"time_ms\":15800,\"time_ms_arr\":[15800,16280.000000000002,16760,17220]},{\"beat_count\":4,\"chord\":\"G\",\"time_ms\":17700,\"time_ms_arr\":[17700,18160,18640,19120]},{\"beat_count\":4,\"chord\":\"Am\",\"time_ms\":19580,\"time_ms_arr\":[19580,20060,20540,21000]},{\"beat_count\":4,\"chord\":\"D\",\"time_ms\":21480,\"time_ms_arr\":[21480,21940,22420,22900]},{\"beat_count\":4,\"chord\":\"G\",\"time_ms\":23360,\"time_ms_arr\":[23360,23840,24320,24780]},{\"beat_count\":4,\"chord\":\"G\",\"time_ms\":25260,\"time_ms_arr\":[25260,25720,26200,26680]},{\"beat_count\":4,\"chord\":\"Am\",\"time_ms\":27140,\"time_ms_arr\":[27140,27620,28100,28560]},{\"beat_count\":4,\"chord\":\"D\",\"time_ms\":29040,\"time_ms_arr\":[29040,29500,29980,30460]},{\"beat_count\":4,\"chord\":\"G\",\"time_ms\":30940,\"time_ms_arr\":[30940,31400,31880,32340.000000000004]},{\"beat_count\":4,\"chord\":\"G\",\"time_ms\":32820,\"time_ms_arr\":[32820,33300,33760,34240]},{\"beat_count\":4,\"chord\":\"Am\",\"time_ms\":34720,\"time_ms_arr\":[34720,35180,35660,36140]},{\"beat_count\":4,\"chord\":\"D\",\"time_ms\":36600,\"time_ms_arr\":[36600,37080,37560,38020]},{\"beat_count\":4,\"chord\":\"G\",\"time_ms\":38500,\"time_ms_arr\":[38500,38960,39440,39920]},{\"beat_count\":4,\"chord\":\"G\",\"time_ms\":40400,\"time_ms_arr\":[40400,40860,41340,41800]},{\"beat_count\":4,\"chord\":\"Am\",\"time_ms\":42280,\"time_ms_arr\":[42280,42760,43220,43700]},{\"beat_count\":4,\"chord\":\"D\",\"time_ms\":44180,\"time_ms_arr\":[44180,44640,45120,45580]},{\"beat_count\":4,\"chord\":\"G\",\"time_ms\":46060,\"time_ms_arr\":[46060,46540,47000,47480]},{\"beat_count\":4,\"chord\":\"D\",\"time_ms\":47960,\"time_ms_arr\":[47960,48420,48900,49380]},{\"beat_count\":4,\"chord\":\"D\",\"time_ms\":49840,\"time_ms_arr\":[49840,50320,50780,51260]},{\"beat_count\":4,\"chord\":\"G\",\"time_ms\":51740,\"time_ms_arr\":[51740,52200,52660,53140]},{\"beat_count\":4,\"chord\":\"G\",\"time_ms\":53620,\"time_ms_arr\":[53620,54100,54560,55040]},{\"beat_count\":4,\"chord\":\"D\",\"time_ms\":55520,\"time_ms_arr\":[55520,55980,56460,56940]},{\"beat_count\":4,\"chord\":\"D\",\"time_ms\":57400,\"time_ms_arr\":[57400,57880,58360,58820]},{\"beat_count\":4,\"chord\":\"G\",\"time_ms\":59300,\"time_ms_arr\":[59300,59760,60240,60720]},{\"beat_count\":4,\"chord\":\"G\",\"time_ms\":61180,\"time_ms_arr\":[61180,61660,62140,62600]},{\"beat_count\":4,\"chord\":\"C\",\"time_ms\":63080,\"time_ms_arr\":[63080,63540,64019.99999999999,64500]},{\"beat_count\":4,\"chord\":\"C\",\"time_ms\":64959.99999999999,\"time_ms_arr\":[64959.99999999999,65440,65900,66380]},{\"beat_count\":4,\"chord\":\"G\",\"time_ms\":66860,\"time_ms_arr\":[66860,67320,67800,68280]},{\"beat_count\":4,\"chord\":\"G\",\"time_ms\":68740,\"time_ms_arr\":[68740,69220,69700,70160]},{\"beat_count\":4,\"chord\":\"D\",\"time_ms\":70640,\"time_ms_arr\":[70640,71120,71580,72060]},{\"beat_count\":4,\"chord\":\"D\",\"time_ms\":72520,\"time_ms_arr\":[72520,73000,73480,73940]},{\"beat_count\":4,\"chord\":\"G\",\"time_ms\":74420,\"time_ms_arr\":[74420,74900,75360,75840]},{\"beat_count\":4,\"chord\":\"G\",\"time_ms\":76300,\"time_ms_arr\":[76300,76780,77260,77740]},{\"beat_count\":4,\"chord\":\"D\",\"time_ms\":78200,\"time_ms_arr\":[78200,78660,79140,79620]},{\"beat_count\":4,\"chord\":\"D\",\"time_ms\":80100,\"time_ms_arr\":[80100,80560,81040,81500]},{\"beat_count\":4,\"chord\":\"G\",\"time_ms\":81980,\"time_ms_arr\":[81980,82460,82920,83400]},{\"beat_count\":4,\"chord\":\"G\",\"time_ms\":83880,\"time_ms_arr\":[83880,84360,84820,85300]},{\"beat_count\":4,\"chord\":\"D\",\"time_ms\":85760,\"time_ms_arr\":[85760,86240,86700,87180]},{\"beat_count\":4,\"chord\":\"D\",\"time_ms\":87660,\"time_ms_arr\":[87660,88140,88600,89080]},{\"beat_count\":4,\"chord\":\"G\",\"time_ms\":89540,\"time_ms_arr\":[89540,90020,90480,90960]},{\"beat_count\":4,\"chord\":\"G\",\"time_ms\":91440,\"time_ms_arr\":[91440,91900,92380,92840]},{\"beat_count\":4,\"chord\":\"C\",\"time_ms\":93320,\"time_ms_arr\":[93320,93800,94280,94740]},{\"beat_count\":4,\"chord\":\"C\",\"time_ms\":95220,\"time_ms_arr\":[95220,95700,96160,96640]},{\"beat_count\":4,\"chord\":\"G\",\"time_ms\":97100,\"time_ms_arr\":[97100,97580,98040,98520]},{\"beat_count\":4,\"chord\":\"G\",\"time_ms\":99000,\"time_ms_arr\":[99000,99480,99940,100420]},{\"beat_count\":4,\"chord\":\"D\",\"time_ms\":100900,\"time_ms_arr\":[100900,101360,101840,102300]},{\"beat_count\":4,\"chord\":\"D\",\"time_ms\":102780,\"time_ms_arr\":[102780,103240,103720,104180]},{\"beat_count\":4,\"chord\":\"G\",\"time_ms\":104660,\"time_ms_arr\":[104660,105120,105600,106080]},{\"beat_count\":4,\"chord\":\"G\",\"time_ms\":106540,\"time_ms_arr\":[106540,107020,107500,107960]},{\"beat_count\":4,\"chord\":\"G\",\"time_ms\":108440,\"time_ms_arr\":[108440,108900,109380,109860]},{\"beat_count\":4,\"chord\":\"Am\",\"time_ms\":110320,\"time_ms_arr\":[110320,110800,111280,111740]},{\"beat_count\":4,\"chord\":\"D\",\"time_ms\":112220,\"time_ms_arr\":[112220,112700,113160,113640]},{\"beat_count\":4,\"chord\":\"G\",\"time_ms\":114120,\"time_ms_arr\":[114120,114580,115060,115540]},{\"beat_count\":4,\"chord\":\"G\",\"time_ms\":116020,\"time_ms_arr\":[116020,116480,116960,117420]},{\"beat_count\":4,\"chord\":\"Am\",\"time_ms\":117880,\"time_ms_arr\":[117880,118360,118840,119300]},{\"beat_count\":4,\"chord\":\"D\",\"time_ms\":119780,\"time_ms_arr\":[119780,120240,120720,121200]},{\"beat_count\":4,\"chord\":\"G\",\"time_ms\":121660,\"time_ms_arr\":[121660,122140,122620,123080]},{\"beat_count\":4,\"chord\":\"G\",\"time_ms\":123560,\"time_ms_arr\":[123560,124040,124500,124980]},{\"beat_count\":4,\"chord\":\"Am\",\"time_ms\":125460,\"time_ms_arr\":[125460,125920,126400,126880]},{\"beat_count\":4,\"chord\":\"D\",\"time_ms\":127360,\"time_ms_arr\":[127360,127820,128300.00000000001,128759.99999999999]},{\"beat_count\":4,\"chord\":\"G\",\"time_ms\":129240.00000000001,\"time_ms_arr\":[129240.00000000001,129699.99999999999,130180,130639.99999999999]},{\"beat_count\":4,\"chord\":\"G\",\"time_ms\":131120,\"time_ms_arr\":[131120,131600,132060,132540]},{\"beat_count\":4,\"chord\":\"Am\",\"time_ms\":133020,\"time_ms_arr\":[133020,133480,133960,134440]},{\"beat_count\":4,\"chord\":\"D\",\"time_ms\":134900,\"time_ms_arr\":[134900,135380,135860,136320]},{\"beat_count\":4,\"chord\":\"G\",\"time_ms\":136800,\"time_ms_arr\":[136800,137260,137740,138200]},{\"beat_count\":4,\"chord\":\"D\",\"time_ms\":138680,\"time_ms_arr\":[138680,139160,139640,140100]},{\"beat_count\":4,\"chord\":\"D\",\"time_ms\":140580,\"time_ms_arr\":[140580,141040,141520,142000]},{\"beat_count\":4,\"chord\":\"G\",\"time_ms\":142460,\"time_ms_arr\":[142460,142940,143420,143880]},{\"beat_count\":4,\"chord\":\"G\",\"time_ms\":144360,\"time_ms_arr\":[144360,144820,145300,145780]},{\"beat_count\":4,\"chord\":\"D\",\"time_ms\":146260,\"time_ms_arr\":[146260,146720,147200,147660]},{\"beat_count\":4,\"chord\":\"D\",\"time_ms\":148140,\"time_ms_arr\":[148140,148620,149100,149560]},{\"beat_count\":4,\"chord\":\"G\",\"time_ms\":150040,\"time_ms_arr\":[150040,150520,150980,151460]},{\"beat_count\":4,\"chord\":\"G\",\"time_ms\":151920,\"time_ms_arr\":[151920,152380,152860,153340]},{\"beat_count\":4,\"chord\":\"C\",\"time_ms\":153800,\"time_ms_arr\":[153800,154280,154760,155220]},{\"beat_count\":4,\"chord\":\"C\",\"time_ms\":155700,\"time_ms_arr\":[155700,156180,156640,157120]},{\"beat_count\":4,\"chord\":\"G\",\"time_ms\":157600,\"time_ms_arr\":[157600,158060,158540,159020]},{\"beat_count\":4,\"chord\":\"G\",\"time_ms\":159480,\"time_ms_arr\":[159480,159960,160440,160900]},{\"beat_count\":4,\"chord\":\"D\",\"time_ms\":161380,\"time_ms_arr\":[161380,161840,162320,162800]},{\"beat_count\":4,\"chord\":\"D\",\"time_ms\":163260,\"time_ms_arr\":[163260,163740,164220,164680]},{\"beat_count\":4,\"chord\":\"G\",\"time_ms\":165160,\"time_ms_arr\":[165160,165620,166100,166580]},{\"beat_count\":4,\"chord\":\"G\",\"time_ms\":167060,\"time_ms_arr\":[167060,167520,167980,168460]},{\"beat_count\":4,\"chord\":\"D\",\"time_ms\":168940,\"time_ms_arr\":[168940,169400,169880,170340]},{\"beat_count\":4,\"chord\":\"D\",\"time_ms\":170820,\"time_ms_arr\":[170820,171280,171760,172240]},{\"beat_count\":4,\"chord\":\"G\",\"time_ms\":172700,\"time_ms_arr\":[172700,173180,173660,174120]},{\"beat_count\":4,\"chord\":\"G\",\"time_ms\":174600,\"time_ms_arr\":[174600,175080,175540,176020]},{\"beat_count\":4,\"chord\":\"D\",\"time_ms\":176500,\"time_ms_arr\":[176500,176960,177440,177920]},{\"beat_count\":4,\"chord\":\"D\",\"time_ms\":178400,\"time_ms_arr\":[178400,178860,179340,179800]},{\"beat_count\":4,\"chord\":\"G\",\"time_ms\":180280,\"time_ms_arr\":[180280,180740,181220,181680]},{\"beat_count\":4,\"chord\":\"G\",\"time_ms\":182160,\"time_ms_arr\":[182160,182640,183120,183600]},{\"beat_count\":4,\"chord\":\"C\",\"time_ms\":184060,\"time_ms_arr\":[184060,184520,185000,185480]},{\"beat_count\":4,\"chord\":\"C\",\"time_ms\":185940,\"time_ms_arr\":[185940,186420,186880,187360]},{\"beat_count\":4,\"chord\":\"G\",\"time_ms\":187840,\"time_ms_arr\":[187840,188300,188780,189260]},{\"beat_count\":4,\"chord\":\"G\",\"time_ms\":189720,\"time_ms_arr\":[189720,190200,190660,191140]},{\"beat_count\":4,\"chord\":\"D\",\"time_ms\":191620,\"time_ms_arr\":[191620,192080,192560,193040]},{\"beat_count\":4,\"chord\":\"D\",\"time_ms\":193500,\"time_ms_arr\":[193500,193980,194460,194940]},{\"beat_count\":4,\"chord\":\"G\",\"time_ms\":195400,\"time_ms_arr\":[195400,195880,196340,196820]},{\"beat_count\":4,\"chord\":\"G\",\"time_ms\":197300,\"time_ms_arr\":[197300,197760,198240,198700]},{\"beat_count\":4,\"chord\":\"D\",\"time_ms\":199180,\"time_ms_arr\":[199180,199660,200140,200600]},{\"beat_count\":4,\"chord\":\"D\",\"time_ms\":201080,\"time_ms_arr\":[201080,201540,202020,202480]},{\"beat_count\":4,\"chord\":\"G\",\"time_ms\":202960,\"time_ms_arr\":[202960,203440,203920,204380]},{\"beat_count\":4,\"chord\":\"G\",\"time_ms\":204860,\"time_ms_arr\":[204860,205320,205800,206260]},{\"beat_count\":4,\"chord\":\"D\",\"time_ms\":206740,\"time_ms_arr\":[206740,207220,207680,208160]},{\"beat_count\":4,\"chord\":\"D\",\"time_ms\":208640,\"time_ms_arr\":[208640,209100,209580,210060]},{\"beat_count\":4,\"chord\":\"G\",\"time_ms\":210520,\"time_ms_arr\":[210520,211000,211480,211940]},{\"beat_count\":4,\"chord\":\"G\",\"time_ms\":212420,\"time_ms_arr\":[212420,212880,213360,213840]},{\"beat_count\":4,\"chord\":\"G\",\"time_ms\":214300,\"time_ms_arr\":[214300,214780,215240,215720]},{\"beat_count\":4,\"chord\":\"Am\",\"time_ms\":216200,\"time_ms_arr\":[216200,216660,217140,217620]},{\"beat_count\":4,\"chord\":\"D\",\"time_ms\":218080,\"time_ms_arr\":[218080,218560,219020,219500]},{\"beat_count\":4,\"chord\":\"G\",\"time_ms\":219960,\"time_ms_arr\":[219960,220440,220920,221400]},{\"beat_count\":4,\"chord\":\"G\",\"time_ms\":221860,\"time_ms_arr\":[221860,222340,222800,223280]},{\"beat_count\":4,\"chord\":\"Am\",\"time_ms\":223760,\"time_ms_arr\":[223760,224220,224700,225180]},{\"beat_count\":4,\"chord\":\"D\",\"time_ms\":225640,\"time_ms_arr\":[225640,226120,226580,227060]},{\"beat_count\":4,\"chord\":\"G\",\"time_ms\":227540,\"time_ms_arr\":[227540,228000,228480,228940]},{\"beat_count\":4,\"chord\":\"G\",\"time_ms\":229440,\"time_ms_arr\":[229440,229900,230360,230840]},{\"beat_count\":4,\"chord\":\"Am\",\"time_ms\":231320,\"time_ms_arr\":[231320,231780,232240,232720]},{\"beat_count\":4,\"chord\":\"D\",\"time_ms\":233200,\"time_ms_arr\":[233200,233680,234140,234620]},{\"beat_count\":4,\"chord\":\"G\",\"time_ms\":235100,\"time_ms_arr\":[235100,235560,236040,236520]},{\"beat_count\":4,\"chord\":\"G\",\"time_ms\":237000,\"time_ms_arr\":[237000,237460,237920,238400]},{\"beat_count\":4,\"chord\":\"Am\",\"time_ms\":238880,\"time_ms_arr\":[238880,239360,239820,240300]}]","lyrics_sync":"[{\"time_ms\":0,\"text\":\"싱그러운 아침 햇살이 \"},{\"time_ms\":22628,\"text\":\"풀잎에 맺힌 이슬 비칠때면\"},{\"time_ms\":28878,\"text\":\"부시시 잠깨인 얼굴로 \"},{\"time_ms\":29512,\"text\":\"해맑은 그대 모습 보았어요\"},{\"time_ms\":32045,\"text\":\"\"},{\"time_ms\":32645,\"text\":\"푸르른 날에는 더욱 더 \"},{\"time_ms\":36761,\"text\":\"사랑하는 마음 알았지만\"},{\"time_ms\":40680,\"text\":\"햇살에 눈부신 이슬은 \"},{\"time_ms\":44177,\"text\":\"차라리 눈을 감고 말았어요\"},{\"time_ms\":46861,\"text\":\"\"},{\"time_ms\":47410,\"text\":\"그대는 풀잎 \"},{\"time_ms\":51060,\"text\":\"나는 이슬 \"},{\"time_ms\":55042,\"text\":\"그대는 이슬 \"},{\"time_ms\":58627,\"text\":\"나는 햇살\"},{\"time_ms\":61879,\"text\":\"\"},{\"time_ms\":62446,\"text\":\"사랑해 그대만을 \"},{\"time_ms\":69943,\"text\":\"우리는 풀잎 사랑\"},{\"time_ms\":77413,\"text\":\"\"},{\"time_ms\":78029,\"text\":\"그대는 풀잎 풀잎 풀잎 \"},{\"time_ms\":81741,\"text\":\"나는 이슬 이슬 이슬\"},{\"time_ms\":85380,\"text\":\"그대는 이슬 이슬 이슬 \"},{\"time_ms\":88846,\"text\":\"나는 햇살 햇살 햇살\"},{\"time_ms\":91861,\"text\":\"\"},{\"time_ms\":92578,\"text\":\"사랑해 그대만을 \"},{\"time_ms\":100243,\"text\":\"우리는 풀잎 사랑\"},{\"time_ms\":108411,\"text\":\"\"},{\"time_ms\":119792,\"text\":\"\"},{\"time_ms\":123608,\"text\":\"빛나던 노을 빛 사랑도 \"},{\"time_ms\":127479,\"text\":\"칸칸이 쓰러지고 말았지만\"},{\"time_ms\":130978,\"text\":\"어둠을 홀로~이 밝히는\"},{\"time_ms\":134812,\"text\":\"나의 사랑 변함 없어요\"},{\"time_ms\":137796,\"text\":\"\"},{\"time_ms\":138296,\"text\":\"그대는 풀잎\"},{\"time_ms\":141844,\"text\":\"나는 이슬\"},{\"time_ms\":145698,\"text\":\"그대는 이슬\"},{\"time_ms\":149880,\"text\":\"나는 햇살\"},{\"time_ms\":152443,\"text\":\"\"},{\"time_ms\":153009,\"text\":\"사랑해 그대만을\"},{\"time_ms\":160827,\"text\":\"우리는 풀잎 사랑\"},{\"time_ms\":168244,\"text\":\"\"},{\"time_ms\":168976,\"text\":\"그대는 풀잎 풀잎 풀잎\"},{\"time_ms\":172145,\"text\":\"나는 이슬 이슬 이슬\"},{\"time_ms\":175911,\"text\":\"그대는 이슬 이슬 이슬\"},{\"time_ms\":179477,\"text\":\"나는 햇살 햇살 햇살\"},{\"time_ms\":182762,\"text\":\"\"},{\"time_ms\":183311,\"text\":\"사랑해 그대 만을\"},{\"time_ms\":191062,\"text\":\"우리는 풀잎 사랑\"},{\"time_ms\":198494,\"text\":\"우리는 풀잎 사랑\"},{\"time_ms\":206362,\"text\":\"우리는 풀잎 사랑\"},{\"time_ms\":214259,\"text\":\"\"},{\"time_ms\":221912,\"text\":\"\"},{\"time_ms\":229479,\"text\":\"\"},{\"time_ms\":236994,\"text\":\"\"}]","date_created":"2023-06-11T22:22:50.000Z","date_updated":"2023-06-12T08:40:07.000Z","cook_step":"served","release_year":1987,"region_type":"KPOP","artist_name":"최성수"}